miniut/__init__.py
miniut/config.py
miniut/console.py
miniut/decorators.py
miniut/log.py
miniut/metaclasses.py
miniut/report.py
miniut/abstract/__init__.py
miniut/abstract/database.py
miniut/exceptions/__init__.py
miniut/exceptions/log.py
miniut-0.1.0.dist-info/LICENSE
miniut-0.1.0.dist-info/METADATA
miniut-0.1.0.dist-info/WHEEL
miniut-0.1.0.dist-info/top_level.txt
miniut-0.1.0.dist-info/RECORD
