Metadata-Version: 2.1
Name: miniut
Version: 0.1.0
Summary: Paquete de utilidades
Home-page: https://github.com/JuanS3/utilities
Author: Juan Sebastián Martínez Serna
License: UNKNOWN
Project-URL: Bug Tracker, https://github.com/JuanS3/utilities/issues
Project-URL: Wiki, https://github.com/JuanS3/utilities/wiki
Platform: UNKNOWN
Classifier: Programming Language :: Python :: 3
Classifier: Programming Language :: Python :: 3.8
Classifier: Programming Language :: Python :: 3.9
Classifier: Programming Language :: Python :: 3.10
Classifier: Programming Language :: Python :: 3.11
Classifier: License :: OSI Approved :: MIT License
Classifier: Operating System :: OS Independent
Requires-Python: >=3.8
